{"defaultBoards":{"startingBoards":["default"]},"boards":{"4thOfJuly":{"id":"4thOfJuly","priority":1,"upgrades":[{"id":"trail","variation":{"name":"boards.customPowers.rocketTrail","overrideIcon":"icon_upgrade_spark_trail","iconForeground":"#FF7B00FF","iconBackground":"#FFFFFF00","powerType":"Vanity","unlockProduct":"4thOfJuly_trail","referenceId":"4thOfJuly.trail"}},{"id":"highSpeed","variation":{"powerType":"SuperSpeed","unlockProduct":"4thOfJuly_highSpeed","referenceId":"4thOfJuly.highSpeed"}}],"defaultVariation":{"name":"boards.4thOfJuly.name","description":"boards.common.specialboard","unlockProduct":"4thOfJuly_default","referenceId":"4thOfJuly.default"},"showDescriptionLabel":true},"aero":{"id":"aero","priority":2,"upgrades":[{"id":"highSpeed","variation":{"powerType":"Speed","unlockProduct":"aero_highSpeed","referenceId":"aero.highSpeed"}},{"id":"glider","variation":{"powerType":"SmoothDrift","unlockProduct":"aero_glider","referenceId":"aero.glider"}}],"defaultVariation":{"name":"boards.aero.name","description":"boards.common.specialboard","unlockProduct":"aero_default","referenceId":"aero.default"},"showDescriptionLabel":true},"bamboo":{"id":"bamboo","priority":3,"upgrades":[],"defaultVariation":{"name":"boards.bamboo.name","unlockProduct":"bamboo_default","referenceId":"bamboo.default"},"showDescriptionLabel":true},"banana":{"id":"banana","priority":4,"upgrades":[],"defaultVariation":{"name":"boards.banana.name","unlockProduct":"banana_default","referenceId":"banana.default"},"showDescriptionLabel":true},"bassBlaster":{"id":"bassBlaster","priority":5,"upgrades":[{"id":"trail","variation":{"name":"boards.customPowers.bassBlasterTrail","overrideIcon":"icon_upgrade_sound_trail","iconForeground":"#2DF4FFFF","iconBackground":"#FFFFFFFF","powerType":"Vanity","unlockProduct":"bassBlaster_trail","referenceId":"bassBlaster.trail"}},{"id":"jumper","variation":{"powerType":"SuperJump","unlockProduct":"bassBlaster_jumper","referenceId":"bassBlaster.jumper"}}],"defaultVariation":{"name":"boards.bassBlaster.name","description":"boards.common.specialboard","unlockProduct":"bassBlaster_default","referenceId":"bassBlaster.default"},"showDescriptionLabel":true},"beach":{"id":"beach","priority":6,"upgrades":[],"defaultVariation":{"name":"boards.beach.name","description":"boards.common.mumbai","unlockProduct":"beach_default","referenceId":"beach.default"},"showDescriptionLabel":true},"bengal":{"id":"bengal","priority":7,"upgrades":[],"defaultVariation":{"name":"boards.bengal.name","description":"boards.common.mumbai","unlockProduct":"bengal_default","referenceId":"bengal.default"},"showDescriptionLabel":true},"betty":{"id":"betty","priority":8,"upgrades":[],"defaultVariation":{"name":"boards.betty.name","unlockProduct":"betty_default","referenceId":"betty.default"},"showDescriptionLabel":true},"bigBlue":{"id":"bigBlue","priority":9,"upgrades":[],"defaultVariation":{"name":"boards.bigBlue.name","unlockProduct":"bigBlue_default","referenceId":"bigBlue.default"},"showDescriptionLabel":true},"bigKahuna":{"id":"bigKahuna","priority":10,"upgrades":[{"id":"glider","variation":{"powerType":"SmoothDrift","unlockProduct":"bigKahuna_glider","referenceId":"bigKahuna.glider"}},{"id":"lowrider","variation":{"powerType":"StayLow","unlockProduct":"bigKahuna_lowrider","referenceId":"bigKahuna.lowrider"}}],"defaultVariation":{"name":"boards.bigKahuna.name","unlockProduct":"bigKahuna_default","referenceId":"bigKahuna.default"}},"birdie":{"id":"birdie","priority":11,"upgrades":[],"defaultVariation":{"name":"boards.birdie.name","description":"boards.common.rio","unlockProduct":"birdie_default","referenceId":"birdie.default"},"showDescriptionLabel":true},"birthday":{"id":"birthday","priority":12,"upgrades":[],"defaultVariation":{"name":"boards.birthday.name","description":"boards.common.birthdayspecial","unlockProduct":"birthday_default","referenceId":"birthday.default"},"showDescriptionLabel":true},"bouncer":{"id":"bouncer","priority":13,"upgrades":[],"defaultVariation":{"name":"boards.bouncer.name","powerType":"SuperJump","unlockProduct":"bouncer_default","referenceId":"bouncer.default","customPowerEffect":"jumperWithSneakers"}},"bubblegum":{"id":"bubblegum","priority":14,"upgrades":[],"defaultVariation":{"name":"boards.bubblegum.name","unlockProduct":"bubblegum_default","referenceId":"bubblegum.default"},"showDescriptionLabel":true},"casket":{"id":"casket","priority":15,"upgrades":[],"defaultVariation":{"name":"boards.casket.name","description":"boards.common.halloweenspecial","unlockProduct":"casket_default","referenceId":"casket.default"},"showDescriptionLabel":true},"chameleon":{"id":"chameleon","priority":16,"upgrades":[],"defaultVariation":{"name":"boards.chameleon.name","unlockProduct":"chameleon_default","referenceId":"chameleon.default"},"showDescriptionLabel":true},"cherry":{"id":"cherry","priority":17,"upgrades":[],"defaultVariation":{"name":"boards.cherry.name","description":"boards.common.specialboard","unlockProduct":"cherry_default","referenceId":"cherry.default"},"showDescriptionLabel":true},"chicky":{"id":"chicky","priority":18,"upgrades":[{"id":"trail","variation":{"name":"boards.customPowers.chickyTrail","overrideIcon":"icon_upgrade_feather","iconForeground":"#FF6C00FF","iconBackground":"#FFFFFFFF","powerType":"Vanity","unlockProduct":"chicky_trail","referenceId":"chicky.trail"}},{"id":"highSpeed","variation":{"powerType":"SuperSpeed","unlockProduct":"chicky_highSpeed","referenceId":"chicky.highSpeed"}}],"defaultVariation":{"name":"boards.chicky.name","unlockProduct":"chicky_default","referenceId":"chicky.default"},"showDescriptionLabel":true},"chooChoo":{"id":"chooChoo","priority":19,"upgrades":[],"defaultVariation":{"name":"boards.chooChoo.name","description":"common.holidayspecial.default","unlockProduct":"chooChoo_default","referenceId":"chooChoo.default"},"showDescriptionLabel":true},"chrome":{"id":"chrome","priority":20,"upgrades":[],"defaultVariation":{"name":"boards.chrome.name","unlockProduct":"chrome_default","referenceId":"chrome.default"},"showDescriptionLabel":true},"clockwork":{"id":"clockwork","priority":21,"upgrades":[],"defaultVariation":{"name":"boards.clockwork.name","unlockProduct":"clockwork_default","referenceId":"clockwork.default"},"showDescriptionLabel":true},"cobra":{"id":"cobra","priority":22,"upgrades":[],"defaultVariation":{"name":"boards.cobra.name","description":"boards.common.marrakesh","unlockProduct":"cobra_default","referenceId":"cobra.default"},"showDescriptionLabel":true},"colorCloud":{"id":"colorCloud","priority":23,"upgrades":[{"id":"highSpeed","variation":{"powerType":"Speed","unlockProduct":"colorCloud_highSpeed","referenceId":"colorCloud.highSpeed"}},{"id":"teleport","variation":{"name":"boards.customPowers.colorSplash","overrideIcon":"icon_upgrade_color_splash","iconForeground":"#FF00C3FF","iconBackground":"#FFFFFF00","powerType":"ZapSideways","unlockProduct":"colorCloud_teleport","referenceId":"colorCloud.teleport"}}],"defaultVariation":{"name":"boards.colorCloud.name","description":"boards.common.specialboard","unlockProduct":"colorCloud_default","referenceId":"colorCloud.default"},"showDescriptionLabel":true},"coral":{"id":"coral","priority":24,"upgrades":[],"defaultVariation":{"name":"boards.coral.name","description":"boards.common.bali","unlockProduct":"coral_default","referenceId":"coral.default"},"showDescriptionLabel":true},"croc":{"id":"croc","priority":25,"upgrades":[],"defaultVariation":{"name":"boards.croc.name","description":"boards.common.cairo","unlockProduct":"croc_default","referenceId":"croc.default"},"showDescriptionLabel":true},"cruiser":{"id":"cruiser","priority":26,"upgrades":[],"defaultVariation":{"name":"boards.cruiser.name","unlockProduct":"cruiser_default","referenceId":"cruiser.default"},"showDescriptionLabel":true},"daredevil":{"id":"daredevil","priority":27,"upgrades":[],"defaultVariation":{"name":"boards.daredevil.name","powerType":"SuperSpeed","unlockProduct":"daredevil_default","referenceId":"daredevil.default"}},"default":{"id":"default","priority":28,"upgrades":[],"defaultVariation":{"name":"boards.default.name","unlockProduct":"default_default","referenceId":"default.default"}},"desertRacer":{"id":"desertRacer","priority":29,"upgrades":[],"defaultVariation":{"name":"boards.desertRacer.name","unlockProduct":"desertRacer_default","referenceId":"desertRacer.default"},"showDescriptionLabel":true},"diablo":{"id":"diablo","priority":30,"upgrades":[],"defaultVariation":{"name":"boards.diablo.name","description":"boards.common.specialboard","unlockProduct":"diablo_default","referenceId":"diablo.default"},"showDescriptionLabel":true},"dragon":{"id":"dragon","priority":31,"upgrades":[],"defaultVariation":{"name":"boards.dragon.name","description":"boards.common.specialboard","unlockProduct":"dragon_default","referenceId":"dragon.default"},"showDescriptionLabel":true},"eagle":{"id":"eagle","priority":32,"upgrades":[],"defaultVariation":{"name":"boards.eagle.name","unlockProduct":"eagle_default","referenceId":"eagle.default"},"showDescriptionLabel":true},"fireDragon":{"id":"fireDragon","priority":33,"upgrades":[],"defaultVariation":{"name":"boards.fireDragon.name","description":"boards.common.specialboard","unlockProduct":"fireDragon_default","referenceId":"fireDragon.default"},"showDescriptionLabel":true},"flamingo":{"id":"flamingo","priority":34,"upgrades":[],"defaultVariation":{"name":"boards.flamingo.name","unlockProduct":"flamingo_default","referenceId":"flamingo.default"},"showDescriptionLabel":true},"flyingHorse":{"id":"flyingHorse","priority":35,"upgrades":[],"defaultVariation":{"name":"boards.flyingHorse.name","unlockProduct":"flyingHorse_default","referenceId":"flyingHorse.default"},"showDescriptionLabel":true},"freestyler":{"id":"freestyler","priority":36,"upgrades":[{"id":"doubleJump","variation":{"powerType":"DoubleJump","unlockProduct":"freestyler_doubleJump","referenceId":"freestyler.doubleJump"}},{"id":"jumper","variation":{"powerType":"SuperJump","unlockProduct":"freestyler_jumper","referenceId":"freestyler.jumper"}}],"defaultVariation":{"name":"boards.freestyler.name","unlockProduct":"freestyler_default","referenceId":"freestyler.default"}},"glacier":{"id":"glacier","priority":37,"upgrades":[],"defaultVariation":{"name":"boards.glacier.name","description":"common.holidayspecial.default","unlockProduct":"glacier_default","referenceId":"glacier.default"},"showDescriptionLabel":true},"goat":{"id":"goat","priority":38,"upgrades":[],"defaultVariation":{"name":"boards.goat.name","unlockProduct":"goat_default","referenceId":"goat.default"},"showDescriptionLabel":true},"gondola":{"id":"gondola","priority":39,"upgrades":[],"defaultVariation":{"name":"boards.gondola.name","description":"boards.common.venice","unlockProduct":"gondola_default","referenceId":"gondola.default"},"showDescriptionLabel":true},"greatWhite":{"id":"greatWhite","priority":40,"upgrades":[{"id":"speed","variation":{"powerType":"SuperSpeed","unlockProduct":"greatWhite_speed","referenceId":"greatWhite.speed"}},{"id":"glider","variation":{"powerType":"SmoothDrift","unlockProduct":"greatWhite_glider","referenceId":"greatWhite.glider"}}],"defaultVariation":{"name":"boards.greatWhite.name","unlockProduct":"greatWhite_default","referenceId":"greatWhite.default"}},"groovy":{"id":"groovy","priority":41,"upgrades":[{"id":"trail","variation":{"name":"boards.customPowers.groovyTrail","overrideIcon":"icon_upgrade_flower","iconForeground":"#FF75DAFF","iconBackground":"#FFFFFF00","powerType":"Vanity","unlockProduct":"groovy_trail","referenceId":"groovy.trail"}}],"defaultVariation":{"name":"boards.groovy.name","unlockProduct":"groovy_default","referenceId":"groovy.default"},"showDescriptionLabel":true},"hammer":{"id":"hammer","priority":42,"upgrades":[],"defaultVariation":{"name":"boards.hammer.name","description":"boards.common.copenhagen","unlockProduct":"hammer_default","referenceId":"hammer.default","customPowerEffect":"visualEffect"},"showDescriptionLabel":true},"hexed":{"id":"hexed","priority":43,"upgrades":[],"defaultVariation":{"name":"boards.hexed.name","description":"boards.common.halloweenspecial","unlockProduct":"hexed_default","referenceId":"hexed.default"},"showDescriptionLabel":true},"hotdog":{"id":"hotdog","priority":44,"upgrades":[],"defaultVariation":{"name":"boards.hotdog.name","unlockProduct":"hotdog_default","referenceId":"hotdog.default"},"showDescriptionLabel":true},"hotrod":{"id":"hotrod","priority":45,"upgrades":[],"defaultVariation":{"name":"boards.hotrod.name","powerType":"Speed","unlockProduct":"hotrod_default","referenceId":"hotrod.default"}},"jazz":{"id":"jazz","priority":46,"upgrades":[{"id":"highSpeed","variation":{"powerType":"Speed","unlockProduct":"jazz_highSpeed","referenceId":"jazz.highSpeed"}},{"id":"superJump","variation":{"powerType":"SuperJump","unlockProduct":"jazz_superJump","referenceId":"jazz.superJump"}}],"defaultVariation":{"name":"boards.jazz.name","description":"boards.common.specialboard","unlockProduct":"jazz_default","referenceId":"jazz.default"},"showDescriptionLabel":true},"jewelled":{"id":"jewelled","priority":47,"upgrades":[],"defaultVariation":{"name":"boards.jewelled.name","description":"boards.common.arabia","unlockProduct":"jewelled_default","referenceId":"jewelled.default"},"showDescriptionLabel":true},"jingles":{"id":"jingles","priority":48,"upgrades":[{"id":"trail","variation":{"name":"boards.customPowers.jinglesTrail","overrideIcon":"icon_upgrade_snow_trail","iconForeground":"#5BFDFFFF","iconBackground":"#FFFFFF00","powerType":"Vanity","unlockProduct":"jingles_trail","referenceId":"jingles.trail"}},{"id":"superJump","variation":{"powerType":"SuperJump","unlockProduct":"jingles_superJump","referenceId":"jingles.superJump"}}],"defaultVariation":{"name":"boards.jingles.name","unlockProduct":"jingles_default","referenceId":"jingles.default"},"showDescriptionLabel":true},"jouster":{"id":"jouster","priority":49,"upgrades":[],"defaultVariation":{"name":"boards.jouster.name","unlockProduct":"jouster_default","referenceId":"jouster.default"},"showDescriptionLabel":true},"kickOff":{"id":"kickOff","priority":50,"upgrades":[],"defaultVariation":{"name":"boards.kickOff.name","unlockProduct":"kickOff_default","referenceId":"kickOff.default"},"showDescriptionLabel":true},"kitty":{"id":"kitty","priority":51,"upgrades":[],"defaultVariation":{"name":"boards.kitty.name","description":"boards.common.tokyo","unlockProduct":"kitty_default","referenceId":"kitty.default"},"showDescriptionLabel":true},"leaf":{"id":"leaf","priority":52,"upgrades":[],"defaultVariation":{"name":"boards.leaf.name","description":"boards.common.specialboard","powerType":"SmoothDrift","unlockProduct":"leaf_default","referenceId":"leaf.default"},"showDescriptionLabel":true},"liberty":{"id":"liberty","priority":53,"upgrades":[],"defaultVariation":{"name":"boards.liberty.name","description":"boards.common.newyork","unlockProduct":"liberty_default","referenceId":"liberty.default"},"showDescriptionLabel":true},"lion":{"id":"lion","priority":54,"upgrades":[],"defaultVariation":{"name":"boards.lion.name","unlockProduct":"lion_default","referenceId":"lion.default"},"showDescriptionLabel":true},"lowrider":{"id":"lowrider","priority":55,"upgrades":[],"defaultVariation":{"name":"boards.lowrider.name","powerType":"StayLow","unlockProduct":"lowrider_default","referenceId":"lowrider.default"}},"lumberjack":{"id":"lumberjack","priority":56,"upgrades":[{"id":"doubleJump","variation":{"powerType":"DoubleJump","unlockProduct":"lumberjack_doubleJump","referenceId":"lumberjack.doubleJump"}},{"id":"lowrider","variation":{"powerType":"StayLow","unlockProduct":"lumberjack_lowrider","referenceId":"lumberjack.lowrider"}}],"defaultVariation":{"name":"boards.lumberjack.name","unlockProduct":"lumberjack_default","referenceId":"lumberjack.default"}},"magicCarpet":{"id":"magicCarpet","priority":57,"upgrades":[{"id":"glider","variation":{"powerType":"SmoothDrift","unlockProduct":"magicCarpet_glider","referenceId":"magicCarpet.glider"}},{"id":"jumper","variation":{"powerType":"SuperJump","unlockProduct":"magicCarpet_jumper","referenceId":"magicCarpet.jumper"}}],"defaultVariation":{"name":"boards.magicCarpet.name","description":"boards.common.specialboard","unlockProduct":"magicCarpet_default","referenceId":"magicCarpet.default"},"showDescriptionLabel":true},"medal":{"id":"medal","priority":58,"upgrades":[],"defaultVariation":{"name":"boards.medal.name","description":"boards.common.specialboard","unlockProduct":"medal_default","referenceId":"medal.default"},"showDescriptionLabel":true},"monster":{"id":"monster","priority":59,"upgrades":[{"id":"highSpeed","variation":{"powerType":"SuperSpeed","unlockProduct":"monster_highSpeed","referenceId":"monster.highSpeed"}},{"id":"superJump","variation":{"powerType":"SuperJump","unlockProduct":"monster_superJump","referenceId":"monster.superJump"}}],"defaultVariation":{"name":"boards.monster.name","unlockProduct":"monster_default","referenceId":"monster.default"}},"moose":{"id":"moose","priority":60,"upgrades":[],"defaultVariation":{"name":"boards.moose.name","description":"boards.common.vancouver","unlockProduct":"moose_default","referenceId":"moose.default"},"showDescriptionLabel":true},"mosaic":{"id":"mosaic","priority":61,"upgrades":[],"defaultVariation":{"name":"boards.mosaic.name","description":"boards.common.barcelona","unlockProduct":"mosaic_default","referenceId":"mosaic.default"},"showDescriptionLabel":true},"naga":{"id":"naga","priority":62,"upgrades":[],"defaultVariation":{"name":"boards.naga.name","description":"boards.common.bali","unlockProduct":"naga_default","referenceId":"naga.default"},"showDescriptionLabel":true},"oldDusty":{"id":"oldDusty","priority":63,"upgrades":[{"id":"trail","variation":{"name":"boards.customPowers.oldDustyTrail","overrideIcon":"icon_upgrade_dust_trail","iconForeground":"#F8D052FF","iconBackground":"#FFFFFF00","powerType":"Vanity","unlockProduct":"oldDusty_trail","referenceId":"oldDusty.trail"}}],"defaultVariation":{"name":"boards.oldDusty.name","description":"boards.common.arabia","unlockProduct":"oldDusty_default","referenceId":"oldDusty.default"},"showDescriptionLabel":true},"orni":{"id":"orni","priority":64,"upgrades":[{"id":"glider","variation":{"powerType":"SmoothDrift","unlockProduct":"orni_glider","referenceId":"orni.glider"}}],"defaultVariation":{"name":"boards.orni.name","description":"boards.common.venice","unlockProduct":"orni_default","referenceId":"orni.default"},"showDescriptionLabel":true},"outback":{"id":"outback","priority":65,"upgrades":[],"defaultVariation":{"name":"boards.outback.name","description":"boards.common.sydney","unlockProduct":"outback_default","referenceId":"outback.default"},"showDescriptionLabel":true},"panda":{"id":"panda","priority":66,"upgrades":[],"defaultVariation":{"name":"boards.panda.name","unlockProduct":"panda_default","referenceId":"panda.default"},"showDescriptionLabel":true},"parasol":{"id":"parasol","priority":67,"upgrades":[],"defaultVariation":{"name":"boards.parasol.name","unlockProduct":"parasol_default","referenceId":"parasol.default"},"showDescriptionLabel":true},"pedal":{"id":"pedal","priority":68,"upgrades":[],"defaultVariation":{"name":"boards.pedal.name","unlockProduct":"pedal_default","referenceId":"pedal.default"},"showDescriptionLabel":true},"phantom":{"id":"phantom","priority":69,"upgrades":[{"id":"teleport","variation":{"powerType":"ZapSideways","unlockProduct":"phantom_teleport","referenceId":"phantom.teleport"}}],"defaultVariation":{"name":"boards.phantom.name","unlockProduct":"phantom_default","referenceId":"phantom.default"},"showDescriptionLabel":true},"pixelHeart":{"id":"pixelHeart","priority":70,"upgrades":[],"defaultVariation":{"name":"boards.pixelHeart.name","description":"boards.common.specialboard","unlockProduct":"pixelHeart_default","referenceId":"pixelHeart.default"},"showDescriptionLabel":true},"prickly":{"id":"prickly","priority":71,"upgrades":[],"defaultVariation":{"name":"boards.prickly.name","unlockProduct":"prickly_default","referenceId":"prickly.default"},"showDescriptionLabel":true},"pumpkin":{"id":"pumpkin","priority":72,"upgrades":[],"defaultVariation":{"name":"boards.pumpkin.name","unlockProduct":"pumpkin_default","referenceId":"pumpkin.default"},"showDescriptionLabel":true},"punk":{"id":"punk","priority":73,"upgrades":[],"defaultVariation":{"name":"boards.punk.name","description":"boards.common.edinburgh","unlockProduct":"punk_default","referenceId":"punk.default"},"showDescriptionLabel":true},"ray":{"id":"ray","priority":74,"upgrades":[],"defaultVariation":{"name":"boards.ray.name","description":"boards.common.sydney","unlockProduct":"ray_default","referenceId":"ray.default"},"showDescriptionLabel":true},"renegade":{"id":"renegade","priority":75,"upgrades":[],"defaultVariation":{"name":"boards.renegade.name","description":"boards.common.venicebeach","unlockProduct":"renegade_default","referenceId":"renegade.default"},"showDescriptionLabel":true},"retroWave":{"id":"retroWave","priority":76,"upgrades":[],"defaultVariation":{"name":"boards.retroWave.name","description":"boards.common.specialboard","unlockProduct":"retroWave_default","referenceId":"retroWave.default"},"showDescriptionLabel":true},"rickshaw":{"id":"rickshaw","priority":77,"upgrades":[],"defaultVariation":{"name":"boards.rickshaw.name","unlockProduct":"rickshaw_default","referenceId":"rickshaw.default"},"showDescriptionLabel":true},"rocket":{"id":"rocket","priority":78,"upgrades":[{"id":"trail","variation":{"name":"boards.customPowers.rocketTrail","overrideIcon":"icon_upgrade_spark_trail","iconForeground":"#FF7B00FF","iconBackground":"#FFFFFF00","powerType":"Vanity","unlockProduct":"rocket_trail","referenceId":"rocket.trail"}},{"id":"highSpeed","variation":{"powerType":"SuperSpeed","unlockProduct":"rocket_highSpeed","referenceId":"rocket.highSpeed"}}],"defaultVariation":{"name":"boards.rocket.name","description":"boards.common.specialboard","unlockProduct":"rocket_default","referenceId":"rocket.default"},"showDescriptionLabel":true},"rockstar":{"id":"rockstar","priority":79,"upgrades":[],"defaultVariation":{"name":"boards.rockstar.name","description":"boards.common.berlin","unlockProduct":"rockstar_default","referenceId":"rockstar.default"},"showDescriptionLabel":true},"roller":{"id":"roller","priority":80,"upgrades":[],"defaultVariation":{"name":"boards.roller.name","description":"boards.common.lasvegas","unlockProduct":"roller_default","referenceId":"roller.default"},"showDescriptionLabel":true},"rose":{"id":"rose","priority":81,"upgrades":[],"defaultVariation":{"name":"boards.rose.name","description":"boards.common.paris","unlockProduct":"rose_default","referenceId":"rose.default"},"showDescriptionLabel":true},"roto":{"id":"roto","priority":82,"upgrades":[],"defaultVariation":{"name":"boards.roto.name","description":"boards.common.specialboard","unlockProduct":"roto_default","referenceId":"roto.default"},"showDescriptionLabel":true},"rudy":{"id":"rudy","priority":83,"upgrades":[],"defaultVariation":{"name":"boards.rudy.name","description":"common.holidayspecial.default","unlockProduct":"rudy_default","referenceId":"rudy.default"},"showDescriptionLabel":true},"scarab":{"id":"scarab","priority":84,"upgrades":[{"id":"glider","variation":{"powerType":"SmoothDrift","unlockProduct":"scarab_glider","referenceId":"scarab.glider"}},{"id":"highSpeed","variation":{"powerType":"SuperSpeed","unlockProduct":"scarab_highSpeed","referenceId":"scarab.highSpeed"}}],"defaultVariation":{"name":"boards.scarab.name","description":"boards.common.specialboard","unlockProduct":"scarab_default","referenceId":"scarab.default"},"showDescriptionLabel":true},"scoot":{"id":"scoot","priority":85,"upgrades":[{"id":"teleport","variation":{"powerType":"ZapSideways","unlockProduct":"scoot_teleport","referenceId":"scoot.teleport"}},{"id":"highSpeed","variation":{"powerType":"SuperSpeed","unlockProduct":"scoot_highSpeed","referenceId":"scoot.highSpeed"}}],"defaultVariation":{"name":"boards.scoot.name","unlockProduct":"scoot_default","referenceId":"scoot.default"}},"scratchy":{"id":"scratchy","priority":86,"upgrades":[],"defaultVariation":{"name":"boards.scratchy.name","unlockProduct":"scratchy_default","referenceId":"scratchy.default"},"showDescriptionLabel":true},"scroll":{"id":"scroll","priority":87,"upgrades":[],"defaultVariation":{"name":"boards.scroll.name","unlockProduct":"scroll_default","referenceId":"scroll.default"},"showDescriptionLabel":true},"skullFire":{"id":"skullFire","priority":88,"upgrades":[{"id":"doubleJump","variation":{"powerType":"DoubleJump","unlockProduct":"skullFire_doubleJump","referenceId":"skullFire.doubleJump"}},{"id":"highSpeed","variation":{"powerType":"SuperSpeed","unlockProduct":"skullFire_highSpeed","referenceId":"skullFire.highSpeed"}}],"defaultVariation":{"name":"boards.skullFire.name","unlockProduct":"skullFire_default","referenceId":"skullFire.default"}},"sleigh":{"id":"sleigh","priority":89,"upgrades":[],"defaultVariation":{"name":"boards.sleigh.name","unlockProduct":"sleigh_default","referenceId":"sleigh.default"},"showDescriptionLabel":true},"snowflake":{"id":"snowflake","priority":90,"upgrades":[],"defaultVariation":{"name":"boards.snowflake.name","unlockProduct":"snowflake_default","referenceId":"snowflake.default"},"showDescriptionLabel":true},"spaceship":{"id":"spaceship","priority":91,"upgrades":[],"defaultVariation":{"name":"boards.spaceship.name","description":"boards.common.specialboard","unlockProduct":"spaceship_default","referenceId":"spaceship.default"},"showDescriptionLabel":true},"speeder":{"id":"speeder","priority":92,"upgrades":[],"defaultVariation":{"name":"boards.speeder.name","description":"boards.common.monaco","powerType":"Speed","unlockProduct":"speeder_default","referenceId":"speeder.default"},"showDescriptionLabel":true},"splash":{"id":"splash","priority":93,"upgrades":[],"defaultVariation":{"name":"boards.splash.name","unlockProduct":"splash_default","referenceId":"splash.default"},"showDescriptionLabel":true},"stallion":{"id":"stallion","priority":94,"upgrades":[{"id":"trail","variation":{"name":"boards.customPowers.stallionTrail","overrideIcon":"icon_upgrade_horseshoe_trail","iconForeground":"#FFA700FF","iconBackground":"#FFFFFF00","powerType":"Vanity","unlockProduct":"stallion_trail","referenceId":"stallion.trail"}},{"id":"jumper","variation":{"powerType":"SuperJump","unlockProduct":"stallion_jumper","referenceId":"stallion.jumper"}}],"defaultVariation":{"name":"boards.stallion.name","description":"boards.common.specialboard","unlockProduct":"stallion_default","referenceId":"stallion.default"},"showDescriptionLabel":true},"starboard":{"id":"starboard","priority":95,"upgrades":[{"id":"trail","variation":{"name":"boards.customPowers.starBoardTrail","overrideIcon":"icon_upgrade_star_trail","iconForeground":"#FF6D00FF","iconBackground":"#FFFFFF00","powerType":"Vanity","unlockProduct":"starboard_trail","referenceId":"starboard.trail"}},{"id":"doubleJump","variation":{"powerType":"DoubleJump","unlockProduct":"starboard_doubleJump","referenceId":"starboard.doubleJump"}}],"defaultVariation":{"name":"boards.starboard.name","unlockProduct":"starboard_default","referenceId":"starboard.default"}},"starcruiser":{"id":"starcruiser","priority":96,"upgrades":[],"defaultVariation":{"name":"boards.starcruiser.name","description":"boards.common.houston","unlockProduct":"starcruiser_default","referenceId":"starcruiser.default"},"showDescriptionLabel":true},"sunset":{"id":"sunset","priority":97,"upgrades":[{"id":"trail","variation":{"name":"boards.customPowers.sunsetTrail","overrideIcon":"icon_upgrade_pink_trail","iconForeground":"#FF25D8FF","iconBackground":"#FFFFFFFF","powerType":"Vanity","unlockProduct":"sunset_trail","referenceId":"sunset.trail"}},{"id":"glider","variation":{"powerType":"SmoothDrift","unlockProduct":"sunset_glider","referenceId":"sunset.glider"}}],"defaultVariation":{"name":"boards.sunset.name","unlockProduct":"sunset_default","referenceId":"sunset.default"}},"superhero":{"id":"superhero","priority":98,"upgrades":[{"id":"teleport","variation":{"powerType":"ZapSideways","unlockProduct":"superhero_teleport","referenceId":"superhero.teleport"}},{"id":"jumper","variation":{"powerType":"SuperJump","unlockProduct":"superhero_jumper","referenceId":"superhero.jumper"}}],"defaultVariation":{"name":"boards.superhero.name","unlockProduct":"superhero_default","referenceId":"superhero.default"}},"sweetheart":{"id":"sweetheart","priority":99,"upgrades":[],"defaultVariation":{"name":"boards.sweetheart.name","description":"boards.common.specialboard","unlockProduct":"sweetheart_default","referenceId":"sweetheart.default"},"showDescriptionLabel":true},"teddy":{"id":"teddy","priority":100,"upgrades":[],"defaultVariation":{"name":"boards.teddy.name","unlockProduct":"teddy_default","referenceId":"teddy.default"},"showDescriptionLabel":true},"teleporter":{"id":"teleporter","priority":101,"upgrades":[],"defaultVariation":{"name":"boards.teleporter.name","powerType":"ZapSideways","unlockProduct":"teleporter_default","referenceId":"teleporter.default"}},"thunderbolt":{"id":"thunderbolt","priority":102,"upgrades":[],"defaultVariation":{"name":"boards.thunderbolt.name","description":"boards.common.greece","unlockProduct":"thunderbolt_default","referenceId":"thunderbolt.default"},"showDescriptionLabel":true},"tiki":{"id":"tiki","priority":103,"upgrades":[],"defaultVariation":{"name":"boards.tiki.name","description":"boards.common.hawaii","unlockProduct":"tiki_default","referenceId":"tiki.default"},"showDescriptionLabel":true},"toucan":{"id":"toucan","priority":104,"upgrades":[],"defaultVariation":{"name":"boards.toucan.name","description":"boards.common.rio","unlockProduct":"toucan_default","referenceId":"toucan.default"},"showDescriptionLabel":true},"tumi":{"id":"tumi","priority":105,"upgrades":[{"id":"teleport","variation":{"powerType":"ZapSideways","unlockProduct":"tumi_teleport","referenceId":"tumi.teleport"}}],"defaultVariation":{"name":"boards.tumi.name","unlockProduct":"tumi_default","referenceId":"tumi.default"},"showDescriptionLabel":true},"turtle":{"id":"turtle","priority":106,"upgrades":[{"id":"trail","variation":{"name":"boards.customPowers.turtleTrail","overrideIcon":"icon_upgrade_pink_trail","iconForeground":"#5DF4FFFF","iconBackground":"#FFFFFF00","powerType":"Vanity","unlockProduct":"turtle_trail","referenceId":"turtle.trail"}}],"defaultVariation":{"name":"boards.turtle.name","unlockProduct":"turtle_default","referenceId":"turtle.default"},"showDescriptionLabel":true},"ukulele":{"id":"ukulele","priority":107,"upgrades":[],"defaultVariation":{"name":"boards.ukulele.name","description":"boards.common.hawaii","unlockProduct":"ukulele_default","referenceId":"ukulele.default"},"showDescriptionLabel":true},"waveRider":{"id":"waveRider","priority":108,"upgrades":[],"defaultVariation":{"name":"boards.waveRider.name","description":"boards.common.sydney","unlockProduct":"waveRider_default","referenceId":"waveRider.default"},"showDescriptionLabel":true},"wayfarer":{"id":"wayfarer","priority":109,"upgrades":[{"id":"glider","variation":{"powerType":"SmoothDrift","unlockProduct":"wayfarer_glider","referenceId":"wayfarer.glider"}}],"defaultVariation":{"name":"boards.wayfarer.name","unlockProduct":"wayfarer_default","referenceId":"wayfarer.default"},"showDescriptionLabel":true},"windglider":{"id":"windglider","priority":110,"upgrades":[],"defaultVariation":{"name":"boards.windglider.name","powerType":"SmoothDrift","unlockProduct":"windglider_default","referenceId":"windglider.default"}},"woody":{"id":"woody","priority":111,"upgrades":[],"defaultVariation":{"name":"boards.woody.name","unlockProduct":"woody_default","referenceId":"woody.default"},"showDescriptionLabel":true},"yellowCab":{"id":"yellowCab","priority":112,"upgrades":[],"defaultVariation":{"name":"boards.yellowCab.name","description":"boards.common.newyork","unlockProduct":"yellowCab_default","referenceId":"yellowCab.default"},"showDescriptionLabel":true},"beelzebook":{"id":"beelzebook","priority":113,"upgrades":[],"defaultVariation":{"name":"boards.beelzebook.name","unlockProduct":"beelzebook_default","referenceId":"beelzebook.default"},"showDescriptionLabel":true},"nflpaBarkley":{"id":"nflpaBarkley","priority":114,"upgrades":[],"defaultVariation":{"name":"boards.nflpaBarkley.name","description":"boards.common.nflpaboard","unlockProduct":"nflpaBarkley_default","referenceId":"nflpaBarkley.default"}},"nflpaBeckham":{"id":"nflpaBeckham","priority":115,"upgrades":[],"defaultVariation":{"name":"boards.nflpaBeckham.name","description":"boards.common.nflpaboard","unlockProduct":"nflpaBeckham_default","referenceId":"nflpaBeckham.default"}},"nflpaBrady":{"id":"nflpaBrady","priority":116,"upgrades":[],"defaultVariation":{"name":"boards.nflpaBrady.name","description":"boards.common.nflpaboard","unlockProduct":"nflpaBrady_default","referenceId":"nflpaBrady.default"}},"nflpaJackson":{"id":"nflpaJackson","priority":117,"upgrades":[],"defaultVariation":{"name":"boards.nflpaJackson.name","description":"boards.common.nflpaboard","unlockProduct":"nflpaJackson_default","referenceId":"nflpaJackson.default"}},"nflpaMahomes":{"id":"nflpaMahomes","priority":118,"upgrades":[],"defaultVariation":{"name":"boards.nflpaMahomes.name","description":"boards.common.nflpaboard","unlockProduct":"nflpaMahomes_default","referenceId":"nflpaMahomes.default"}},"nflpaPrescott":{"id":"nflpaPrescott","priority":119,"upgrades":[],"defaultVariation":{"name":"boards.nflpaPrescott.name","description":"boards.common.nflpaboard","unlockProduct":"nflpaPrescott_default","referenceId":"nflpaPrescott.default"}},"sakarBlueIce":{"id":"sakarBlueIce","priority":120,"upgrades":[],"defaultVariation":{"name":"boards.sakarBlueIce.name","description":"boards.common.specialboard","unlockProduct":"sakarBlueIce_default","referenceId":"sakarBlueIce.default"},"showDescriptionLabel":true},"sakarCrew":{"id":"sakarCrew","priority":121,"upgrades":[],"defaultVariation":{"name":"boards.sakarCrew.name","description":"boards.common.specialboard","unlockProduct":"sakarCrew_default","referenceId":"sakarCrew.default"},"showDescriptionLabel":true},"sakarCrewCrush":{"id":"sakarCrewCrush","priority":122,"upgrades":[],"defaultVariation":{"name":"boards.sakarCrewCrush.name","description":"boards.common.specialboard","unlockProduct":"sakarCrewCrush_default","referenceId":"sakarCrewCrush.default"},"showDescriptionLabel":true},"sakarSurfSpray":{"id":"sakarSurfSpray","priority":123,"upgrades":[],"defaultVariation":{"name":"boards.sakarSurfSpray.name","description":"boards.common.specialboard","unlockProduct":"sakarSurfSpray_default","referenceId":"sakarSurfSpray.default"},"showDescriptionLabel":true},"sakarWildStyle":{"id":"sakarWildStyle","priority":124,"upgrades":[],"defaultVariation":{"name":"boards.sakarWildStyle.name","description":"boards.common.specialboard","unlockProduct":"sakarWildStyle_default","referenceId":"sakarWildStyle.default"},"showDescriptionLabel":true},"endeavour":{"id":"endeavour","priority":125,"upgrades":[],"defaultVariation":{"name":"boards.endeavour.name","description":"boards.common.space","unlockProduct":"endeavour_default","referenceId":"endeavour.default"},"showDescriptionLabel":true},"discovery":{"id":"discovery","priority":126,"upgrades":[],"defaultVariation":{"name":"boards.discovery.name","description":"boards.common.space","unlockProduct":"discovery_default","referenceId":"discovery.default"},"showDescriptionLabel":true},"secretSociety":{"id":"secretSociety","priority":127,"upgrades":[],"defaultVariation":{"name":"boards.secretSociety.name","description":"boards.common.specialboard","unlockProduct":"secretSociety_default","referenceId":"secretSociety.default"},"showDescriptionLabel":true},"crane":{"id":"crane","priority":128,"upgrades":[],"defaultVariation":{"name":"boards.crane.name","description":"boards.common.specialboard","unlockProduct":"crane_default","referenceId":"crane.default"},"showDescriptionLabel":true},"buddyBear":{"id":"buddyBear","priority":129,"upgrades":[],"defaultVariation":{"name":"boards.buddyBear.name","description":"boards.common.berlin","unlockProduct":"buddyBear_default","referenceId":"buddyBear.default"},"showDescriptionLabel":true},"uprock":{"id":"uprock","priority":130,"upgrades":[],"defaultVariation":{"name":"boards.uprock.name","description":"boards.common.newyork","unlockProduct":"uprock_default","referenceId":"uprock.default"},"showDescriptionLabel":true},"bunny":{"id":"bunny","priority":131,"upgrades":[],"defaultVariation":{"name":"boards.bunny.name","description":"boards.common.oxford","unlockProduct":"bunny_default","referenceId":"bunny.default"},"showDescriptionLabel":true},"shuttle":{"id":"shuttle","priority":132,"upgrades":[],"defaultVariation":{"name":"boards.shuttle.name","description":"boards.common.houston","unlockProduct":"shuttle_default","referenceId":"shuttle.default"},"showDescriptionLabel":true},"viking":{"id":"viking","priority":133,"upgrades":[],"defaultVariation":{"name":"boards.viking.name","description":"boards.common.copenhagen","unlockProduct":"viking_default","referenceId":"viking.default"},"showDescriptionLabel":true},"birthday2021":{"id":"birthday2021","priority":134,"upgrades":[],"defaultVariation":{"name":"boards.birthday2021.name","description":"boards.common.birthdayspecial","unlockProduct":"birthday2021_default","referenceId":"birthday2021.default"},"showDescriptionLabel":true},"dragonBoat":{"id":"dragonBoat","priority":135,"upgrades":[],"defaultVariation":{"name":"boards.dragonBoat.name","unlockProduct":"dragonBoat_default","referenceId":"dragonBoat.default"},"showDescriptionLabel":true},"paintPalette":{"id":"paintPalette","priority":136,"upgrades":[],"defaultVariation":{"name":"boards.paintPalette.name","description":"boards.common.paris","unlockProduct":"paintPalette_default","referenceId":"paintPalette.default"},"showDescriptionLabel":true},"sakura":{"id":"sakura","priority":137,"upgrades":[],"defaultVariation":{"name":"boards.sakura.name","description":"boards.common.tokyo","unlockProduct":"sakura_default","referenceId":"sakura.default"},"showDescriptionLabel":true},"queenofhearts":{"id":"queenofhearts","priority":138,"upgrades":[],"defaultVariation":{"name":"boards.queenofhearts.name","description":"boards.common.lasvegas","unlockProduct":"queenofhearts_default","referenceId":"queenofhearts.default"},"showDescriptionLabel":true},"camel":{"id":"camel","priority":139,"upgrades":[],"defaultVariation":{"name":"boards.camel.name","description":"boards.common.marrakesh","unlockProduct":"camel_default","referenceId":"camel.default"},"showDescriptionLabel":true},"torito":{"id":"torito","priority":140,"upgrades":[],"defaultVariation":{"name":"boards.torito.name","unlockProduct":"torito_default","referenceId":"torito.default"},"showDescriptionLabel":true},"mapleLeaf":{"id":"mapleLeaf","priority":141,"upgrades":[{"id":"glider","variation":{"powerType":"SmoothDrift","unlockProduct":"mapleLeaf_glider","referenceId":"mapleLeaf.glider"}},{"id":"superJump","variation":{"powerType":"SuperJump","unlockProduct":"mapleLeaf_superJump","referenceId":"mapleLeaf.superJump"}}],"defaultVariation":{"name":"boards.mapleLeaf.name","description":"boards.common.vancouver","unlockProduct":"mapleLeaf_default","referenceId":"mapleLeaf.default"},"showDescriptionLabel":true},"beachPop":{"id":"beachPop","priority":142,"upgrades":[],"defaultVariation":{"name":"boards.beachPop.name","description":"boards.common.venicebeach","unlockProduct":"beachPop_default","referenceId":"beachPop.default"},"showDescriptionLabel":true},"gingerBoom":{"id":"gingerBoom","priority":143,"upgrades":[],"defaultVariation":{"name":"boards.gingerBoom.name","description":"common.holidayspecial.default","unlockProduct":"gingerBoom_default","referenceId":"gingerBoom.default"},"showDescriptionLabel":true},"atomicTile":{"id":"atomicTile","priority":144,"upgrades":[],"defaultVariation":{"name":"boards.atomicTile.name","description":"boards.common.cairo","unlockProduct":"atomicTile_default","referenceId":"atomicTile.default"},"showDescriptionLabel":true},"lunarTiger":{"id":"lunarTiger","priority":145,"upgrades":[],"defaultVariation":{"name":"boards.lunarTiger.name","unlockProduct":"lunarTiger_default","referenceId":"lunarTiger.default"},"showDescriptionLabel":true},"astronave":{"id":"astronave","priority":146,"upgrades":[],"defaultVariation":{"name":"boards.astronave.name","description":"boards.common.barcelona","unlockProduct":"astronave_default","referenceId":"astronave.default"},"showDescriptionLabel":true},"spring":{"id":"spring","priority":147,"upgrades":[],"defaultVariation":{"name":"boards.spring.name","description":"boards.common.vancouver","unlockProduct":"spring_default","referenceId":"spring.default"},"showDescriptionLabel":true},"rollsRabbit":{"id":"rollsRabbit","priority":148,"upgrades":[],"defaultVariation":{"name":"boards.rollsRabbit.name","description":"boards.common.oxford","unlockProduct":"rollsRabbit_default","referenceId":"rollsRabbit.default"},"showDescriptionLabel":true},"crashTest":{"id":"crashTest","priority":149,"upgrades":[{"id":"highSpeed","variation":{"powerType":"SuperSpeed","unlockProduct":"crashTest_highSpeed","referenceId":"crashTest.highSpeed"}}],"defaultVariation":{"name":"boards.crashTest.name","description":"boards.common.monaco","unlockProduct":"crashTest_default","referenceId":"crashTest.default"},"showDescriptionLabel":true},"superSurfer":{"id":"superSurfer","priority":150,"upgrades":[],"defaultVariation":{"name":"boards.superSurfer.name","description":"boards.common.birthdayspecial","powerType":"SuperSpeed","unlockProduct":"superSurfer_default","referenceId":"superSurfer.default"},"showDescriptionLabel":true},"birthday2022":{"id":"birthday2022","priority":151,"upgrades":[],"defaultVariation":{"name":"boards.birthday2022.name","description":"boards.common.birthdayspecial","unlockProduct":"birthday2022_default","referenceId":"birthday2022.default"},"showDescriptionLabel":true},"trickster":{"id":"trickster","priority":152,"upgrades":[],"defaultVariation":{"name":"boards.trickster.name","description":"boards.common.birthdayspecial","powerType":"SuperJump","unlockProduct":"trickster_default","referenceId":"trickster.default"},"showDescriptionLabel":true},"boombastic":{"id":"boombastic","priority":153,"upgrades":[],"defaultVariation":{"name":"boards.boombastic.name","description":"boards.common.birthdayspecial","powerType":"SmoothDrift","unlockProduct":"boombastic_default","referenceId":"boombastic.default"},"showDescriptionLabel":true},"magNeatO":{"id":"magNeatO","priority":154,"upgrades":[],"defaultVariation":{"name":"boards.magNeatO.name","description":"boards.common.birthdayspecial","powerType":"ZapSideways","unlockProduct":"magNeatO_default","referenceId":"magNeatO.default"},"showDescriptionLabel":true},"ssskater":{"id":"ssskater","priority":155,"upgrades":[],"defaultVariation":{"name":"boards.ssskater.name","description":"boards.common.greece","unlockProduct":"ssskater_default","referenceId":"ssskater.default"},"showDescriptionLabel":true},"moped":{"id":"moped","priority":156,"upgrades":[],"defaultVariation":{"name":"boards.moped.name","unlockProduct":"moped_default","referenceId":"moped.default"},"showDescriptionLabel":true},"aeroFish":{"id":"aeroFish","priority":157,"upgrades":[{"id":"highSpeed","variation":{"powerType":"SuperSpeed","unlockProduct":"aeroFish_highSpeed","referenceId":"aeroFish.highSpeed"}}],"defaultVariation":{"name":"boards.aeroFish.name","description":"boards.common.mumbai","unlockProduct":"aeroFish_default","referenceId":"aeroFish.default"},"showDescriptionLabel":true},"smokingSlime":{"id":"smokingSlime","priority":158,"upgrades":[{"id":"highSpeed","variation":{"powerType":"SuperSpeed","unlockProduct":"smokingSlime_highSpeed","referenceId":"smokingSlime.highSpeed"}},{"id":"superJump","variation":{"powerType":"SuperJump","unlockProduct":"smokingSlime_superJump","referenceId":"smokingSlime.superJump"}}],"defaultVariation":{"name":"boards.smokingSlime.name","unlockProduct":"smokingSlime_default","referenceId":"smokingSlime.default"},"showDescriptionLabel":true},"nightlute":{"id":"nightlute","priority":159,"upgrades":[{"id":"highSpeed","variation":{"powerType":"SuperSpeed","unlockProduct":"nightlute_highSpeed","referenceId":"nightlute.highSpeed"}}],"defaultVariation":{"name":"boards.nightlute.name","description":"boards.common.luoyang","unlockProduct":"nightlute_default","referenceId":"nightlute.default"},"showDescriptionLabel":true},"zuperzapper":{"id":"zuperzapper","priority":160,"upgrades":[],"defaultVariation":{"name":"boards.zuperzapper.name","description":"boards.common.birthdayspecial","powerType":"SuperSpeed","unlockProduct":"zuperzapper_default","referenceId":"zuperzapper.default"},"showDescriptionLabel":true},"snowCloud":{"id":"snowCloud","priority":161,"upgrades":[],"defaultVariation":{"name":"boards.snowCloud.name","description":"common.holidayspecial.default","unlockProduct":"snowcloud_default","referenceId":"snowCloud.default"},"showDescriptionLabel":true},"xmas2022":{"id":"xmas2022","priority":162,"upgrades":[],"defaultVariation":{"name":"boards.wrapped.name","description":"common.holidayspecial.default","unlockProduct":"xmas2022_default","referenceId":"xmas2022.default"},"showDescriptionLabel":true},"hohohoverboard":{"id":"hohohoverboard","priority":163,"upgrades":[],"defaultVariation":{"name":"boards.hoHoHoverboard.name","description":"common.holidayspecial.default","unlockProduct":"hohohoverboard_default","referenceId":"hohohoverboard.default"},"showDescriptionLabel":true},"carpdiem":{"id":"carpdiem","priority":164,"upgrades":[],"defaultVariation":{"name":"boards.carpdiem.name","description":"common.holidayspecial.default","powerType":"SmoothDrift","unlockProduct":"carpdiem_default","referenceId":"carpdiem.default"},"showDescriptionLabel":true},"ghastlyglider":{"id":"ghastlyglider","priority":165,"upgrades":[],"defaultVariation":{"name":"boards.ghastlyglider.name","description":"boards.common.oxford","unlockProduct":"ghastlyglider_default","referenceId":"ghastlyglider.default"},"showDescriptionLabel":true},"fanTastic":{"id":"fanTastic","priority":166,"upgrades":[],"defaultVariation":{"name":"boards.fanTastic.name","description":"boards.common.barcelona","powerType":"SuperSpeed","unlockProduct":"fanTastic_default","referenceId":"fanTastic.default"},"showDescriptionLabel":true},"viperfish":{"id":"viperfish","priority":167,"upgrades":[],"defaultVariation":{"name":"boards.viperfish.name","description":"boards.common.underwater","powerType":"SmoothDrift","unlockProduct":"viperfish_default","referenceId":"viperfish.default"},"showDescriptionLabel":true},"iscream":{"id":"iscream","priority":168,"upgrades":[],"defaultVariation":{"name":"boards.iscream.name","description":"boards.common.edinburgh","powerType":"None","unlockProduct":"iscream_default","referenceId":"iscream.default"},"showDescriptionLabel":true},"tagger":{"id":"tagger","priority":169,"upgrades":[],"defaultVariation":{"name":"boards.tagger.name","description":"boards.common.chicago","powerType":"DoubleJump","unlockProduct":"tagger_default","referenceId":"tagger.default"},"showDescriptionLabel":true}},"$schema":"../schema/boards_schema.json"}